setup.py
highlander/__init__.py
highlander/exceptions.py
highlander/highlander.py
highlander_one.egg-info/PKG-INFO
highlander_one.egg-info/SOURCES.txt
highlander_one.egg-info/dependency_links.txt
highlander_one.egg-info/requires.txt
highlander_one.egg-info/top_level.txt