Metadata-Version: 1.1
Name: highlander-one
Version: 0.1.1
Summary: A simple decorator to ensure that your program is only running once on a system.
Home-page: https://github.com/chriscannon/highlander
Author: Christopher T. Cannon
Author-email: christophertcannon@gmail.com
License: MIT
Download-URL: https://github.com/chriscannon/highlander/tarball/0.1.1
Platform: UNKNOWN
Classifier: Development Status :: 4 - Beta
Classifier: Intended Audience :: Developers
Classifier: License :: OSI Approved :: MIT License
Classifier: Programming Language :: Python :: 2
Classifier: Programming Language :: Python :: 2.6
Classifier: Programming Language :: Python :: 2.7
Classifier: Programming Language :: Python :: 3
Classifier: Programming Language :: Python :: 3.2
Classifier: Programming Language :: Python :: 3.3
Classifier: Programming Language :: Python :: 3.4
